{"id":"S19","summaryText":"[SUMMARY S19] 25.9 KB | code | 600 lines\n<path>C:\\opencode\\khoj\\khoj-repo\\tests\\test_secrets_vault.py</path>\n<type>file</type>\n<content>1: \"\"\"Tests for the secrets_vault module - HashiCorp Vault adapter.\n2: \n3: These tests use mocks to avoid requiring a real Vault server.\n→ Use /swarm retrieve S19 for full content","fullOutput":"<path>C:\\opencode\\khoj\\khoj-repo\\tests\\test_secrets_vault.py</path>\n<type>file</type>\n<content>1: \"\"\"Tests for the secrets_vault module - HashiCorp Vault adapter.\n2: \n3: These tests use mocks to avoid requiring a real Vault server.\n4: \"\"\"\n5: import os\n6: import sys\n7: import unittest\n8: from unittest.mock import patch, MagicMock, Mock\n9: \n10: # Mock hvac before any imports\n11: sys.modules['hvac'] = MagicMock()\n12: \n13: # Add the src directory to the path\n14: sys.path.insert(0, os.path.join(os.path.dirname(__file__), '..', 'src'))\n15: \n16: # Import after mocking hvac\n17: from khoj.utils.secrets import LdapSecretError\n18: from khoj.utils.secrets_vault import (\n19:     VaultAdapter,\n20:     is_vault_configured,\n21:     get_ldap_credentials_from_vault,\n22:     HVAC_AVAILABLE,\n23: )\n24: \n25: \n26: class TestModuleImport(unittest.TestCase):\n27:     \"\"\"Test that the module imports without errors.\"\"\"\n28: \n29:     def test_module_has_required_attributes(self):\n30:         \"\"\"Verify the secrets_vault module has all required attributes.\"\"\"\n31:         import khoj.utils.secrets_vault as vault_module\n32:         self.assertTrue(hasattr(vault_module, 'VaultAdapter'))\n33:         self.assertTrue(hasattr(vault_module, 'is_vault_configured'))\n34:         self.assertTrue(hasattr(vault_module, 'get_ldap_credentials_from_vault'))\n35:         self.assertTrue(hasattr(vault_module, 'LdapSecretError'))\n36:         self.assertTrue(hasattr(vault_module, 'HVAC_AVAILABLE'))\n37: \n38:     def test_hvac_available_is_true_when_mocked(self):\n39:         \"\"\"Verify HVAC_AVAILABLE is True when hvac is mocked.\"\"\"\n40:         self.assertTrue(HVAC_AVAILABLE)\n41: \n42: \n43: class TestIsVaultConfigured(unittest.TestCase):\n44:     \"\"\"Test is_vault_configured function.\"\"\"\n45: \n46:     @patch.dict(os.environ, {}, clear=True)\n47:     def test_returns_false_when_no_env_vars_set(self):\n48:         \"\"\"Test that False is returned when no Vault env vars are set.\"\"\"\n49:         result = is_vault_configured()\n50:         self.assertFalse(result)\n51: \n52:     @patch.dict(os.environ, {\"KHOJ_VAULT_ADDR\": \"http://vault:8200\"}, clear=True)\n53:     def test_returns_false_when_only_addr_set(self):\n54:         \"\"\"Test that False is returned when only KHOJ_VAULT_ADDR is set.\"\"\"\n55:         result = is_vault_configured()\n56:         self.assertFalse(result)\n57: \n58:     @patch.dict(os.environ, {\"KHOJ_VAULT_TOKEN\": \"test-token\"}, clear=True)\n59:     def test_returns_false_when_only_token_set(self):\n60:         \"\"\"Test that False is returned when only KHOJ_VAULT_TOKEN is set.\"\"\"\n61:         result = is_vault_configured()\n62:         self.assertFalse(result)\n63: \n64:     @patch.dict(os.environ, {\"KHOJ_VAULT_PATH\": \"secret/data/khoj/ldap\"}, clear=True)\n65:     def test_returns_false_when_only_path_set(self):\n66:         \"\"\"Test that False is returned when only KHOJ_VAULT_PATH is set.\"\"\"\n67:         result = is_vault_configured()\n68:         self.assertFalse(result)\n69: \n70:     @patch.dict(os.environ, {\n71:         \"KHOJ_VAULT_ADDR\": \"http://vault:8200\",\n72:         \"KHOJ_VAULT_TOKEN\": \"test-token\"\n73:     }, clear=True)\n74:     def test_returns_false_when_only_addr_and_token_set(self):\n75:         \"\"\"Test that False is returned when only addr and token are set.\"\"\"\n76:         result = is_vault_configured()\n77:         self.assertFalse(result)\n78: \n79:     @patch.dict(os.environ, {\n80:         \"KHOJ_VAULT_ADDR\": \"http://vault:8200\",\n81:         \"KHOJ_VAULT_TOKEN\": \"test-token\",\n82:         \"KHOJ_VAULT_PATH\": \"secret/data/khoj/ldap\"\n83:     }, clear=True)\n84:     def test_returns_true_when_all_required_env_vars_set(self):\n85:         \"\"\"Test that True is returned when all required Vault env vars are set.\"\"\"\n86:         result = is_vault_configured()\n87:         self.assertTrue(result)\n88: \n89:     @patch.dict(os.environ, {\n90:         \"KHOJ_VAULT_ADDR\": \"\",\n91:         \"KHOJ_VAULT_TOKEN\": \"test-token\",\n92:         \"KHOJ_VAULT_PATH\": \"secret/data/khoj/ldap\"\n93:     }, clear=True)\n94:     def test_returns_false_when_addr_is_empty(self):\n95:         \"\"\"Test that False is returned when KHOJ_VAULT_ADDR is empty string.\"\"\"\n96:         result = is_vault_configured()\n97:         self.assertFalse(result)\n98: \n99:     @patch.dict(os.environ, {\n100:         \"KHOJ_VAULT_ADDR\": \"http://vault:8200\",\n101:         \"KHOJ_VAULT_TOKEN\": \"\",\n102:         \"KHOJ_VAULT_PATH\": \"secret/data/khoj/ldap\"\n103:     }, clear=True)\n104:     def test_returns_false_when_token_is_empty(self):\n105:         \"\"\"Test that False is returned when KHOJ_VAULT_TOKEN is empty string.\"\"\"\n106:         result = is_vault_configured()\n107:         self.assertFalse(result)\n108: \n109:     @patch.dict(os.environ, {\n110:         \"KHOJ_VAULT_ADDR\": \"http://vault:8200\",\n111:         \"KHOJ_VAULT_TOKEN\": \"test-token\",\n112:         \"KHOJ_VAULT_PATH\": \"\"\n113:     }, clear=True)\n114:     def test_returns_false_when_path_is_empty(self):\n115:         \"\"\"Test that False is returned when KHOJ_VAULT_PATH is empty string.\"\"\"\n116:         result = is_vault_configured()\n117:         self.assertFalse(result)\n118: \n119: \n120: class TestVaultAdapterInit(unittest.TestCase):\n121:     \"\"\"Test VaultAdapter initialization.\"\"\"\n122: \n123:     @patch.dict(os.environ, {}, clear=True)\n124:     def test_raises_error_when_env_vars_not_set(self):\n125:         \"\"\"Test that LdapSecretError is raised when Vault env vars are not set.\"\"\"\n126:         with self.assertRaises(LdapSecretError) as context:\n127:             VaultAdapter()\n128:         self.assertIn(\"vault configuration incomplete\", str(context.exception).lower())\n129: \n130:     @patch.dict(os.environ, {\"KHOJ_VAULT_ADDR\": \"http://vault:8200\"}, clear=True)\n131:     def test_raises_error_when_vault_token_not_set(self):\n132:         \"\"\"Test that LdapSecretError is raised when KHOJ_VAULT_TOKEN is not set.\"\"\"\n133:         with self.assertRaises(LdapSecretError) as context:\n134:             VaultAdapter()\n135:         self.assertIn(\"vault configuration incomplete\", str(context.exception).lower())\n136: \n137:     @patch.dict(os.environ, {\n138:         \"KHOJ_VAULT_ADDR\": \"http://vault:8200\",\n139:         \"KHOJ_VAULT_TOKEN\": \"test-token\"\n140:     }, clear=True)\n141:     @patch('khoj.utils.secrets_vault.hvac.Client')\n142:     def test_initializes_client_when_env_vars_set(self, mock_client_class):\n143:         \"\"\"Test that Vault client is initialized when env vars are set.\"\"\"\n144:         mock_client = MagicMock()\n145:         mock_client.is_authenticated.return_value = True\n146:         mock_client_class.return_value = mock_client\n147:         \n148:         adapter = VaultAdapter()\n149:         \n150:         mock_client_class.assert_called_once_with(\n151:             url=\"http://vault:8200\",\n152:             token=\"test-token\"\n153:         )\n154:         self.assertEqual(adapter.client, mock_client)\n155: \n156:     @patch.dict(os.environ, {\n157:         \"KHOJ_VAULT_ADDR\": \"http://vault:8200\",\n158:         \"KHOJ_VAULT_TOKEN\": \"test-token\"\n159:     }, clear=True)\n160:     @patch('khoj.utils.secrets_vault.hvac.Client')\n161:     def test_raises_error_when_authentication_fails(self, mock_client_class):\n162:         \"\"\"Test that LdapSecretError is raised when Vault authentication fails.\"\"\"\n163:         mock_client = MagicMock()\n164:         mock_client.is_authenticated.return_value = False\n165:         mock_client_class.return_value = mock_client\n166:         \n167:         with self.assertRaises(LdapSecretError) as context:\n168:             VaultAdapter()\n169:         self.assertIn(\"authentication failed\", str(context.exception).lower())\n170: \n171:     @patch.dict(os.environ, {\n172:         \"KHOJ_VAULT_ADDR\": \"http://vault:8200\",\n173:         \"KHOJ_VAULT_TOKEN\": \"test-token\"\n174:     }, clear=True)\n175:     @patch('khoj.utils.secrets_vault.hvac.Client')\n176:     def test_raises_error_when_client_creation_fails(self, mock_client_class):\n177:         \"\"\"Test that LdapSecretError is raised when client creation fails.\"\"\"\n178:         mock_client_class.side_effect = Exception(\"Connection refused\")\n179:         \n180:         with self.assertRaises(LdapSecretError) as context:\n181:             VaultAdapter()\n182:         self.assertIn(\"failed to connect\", str(context.exception).lower())\n183: \n184:     @patch.dict(os.environ, {\n185:         \"KHOJ_VAULT_ADDR\": \"http://vault:8200\",\n186:         \"KHOJ_VAULT_TOKEN\": \"test-token\",\n187:         \"KHOJ_VAULT_CACHE_TTL\": \"600\"\n188:     }, clear=True)\n189:     @patch('khoj.utils.secrets_vault.hvac.Client')\n190:     def test_uses_custom_cache_ttl_from_env(self, mock_client_class):\n191:         \"\"\"Test that custom cache TTL is read from environment.\"\"\"\n192:         mock_client = MagicMock()\n193:         mock_client.is_authenticated.return_value = True\n194:         mock_client_class.return_value = mock_client\n195:         \n196:         adapter = VaultAdapter()\n197:         \n198:         self.assertEqual(adapter._cache_ttl, 600)\n199: \n200: \n201: class TestVaultAdapterGetLdapCredentials(unittest.TestCase):\n202:     \"\"\"Test VaultAdapter.get_ldap_credentials method.\"\"\"\n203: \n204:     def setUp(self):\n205:         \"\"\"Set up test fixtures.\"\"\"\n206:         self.mock_client = MagicMock()\n207:         self.mock_response = {\n208:             \"data\": {\n209:                 \"data\": {\n210:                     \"bind_dn\": \"CN=service,DC=example,DC=com\",\n211:                     \"bind_password\": \"secret_password_123\"\n212:                 }\n213:             }\n214:         }\n215:         self.mock_client.secrets.kv.v2.read_secret_version.return_value = self.mock_response\n216:         self.mock_client.is_authenticated.return_value = True\n217: \n218:     @patch.dict(os.environ, {\n219:         \"KHOJ_VAULT_ADDR\": \"http://vault:8200\",\n220:         \"KHOJ_VAULT_TOKEN\": \"test-token\",\n221:         \"KHOJ_VAULT_PATH\": \"secret/data/khoj/ldap\"\n222:     }, clear=True)\n223:     @patch('khoj.utils.secrets_vault.hvac.Client')\n224:     def test_returns_credentials_from_vault(self, mock_client_class):\n225:         \"\"\"Test that credentials are retrieved from Vault.\"\"\"\n226:         mock_client_class.return_value = self.mock_client\n227:         \n228:         adapter = VaultAdapter()\n229:         bind_dn, bind_password = adapter.get_ldap_credentials()\n230:         \n231:         self.assertEqual(bind_dn, \"CN=service,DC=example,DC=com\")\n232:         self.assertEqual(bind_password, \"secret_password_123\")\n233: \n234:     @patch.dict(os.environ, {\n235:         \"KHOJ_VAULT_ADDR\": \"http://vault:8200\",\n236:         \"KHOJ_VAULT_TOKEN\": \"test-token\",\n237:         \"KHOJ_VAULT_PATH\": \"secret/data/khoj/ldap\"\n238:     }, clear=True)\n239:     @patch('khoj.utils.secrets_vault.hvac.Client')\n240:     def test_uses_correct_vault_path(self, mock_client_class):\n241:         \"\"\"Test that the correct Vault path is used.\"\"\"\n242:         mock_client_class.return_value = self.mock_client\n243:         \n244:         adapter = VaultAdapter()\n245:         adapter.get_ldap_credentials()\n246:         \n247:         self.mock_client.secrets.kv.v2.read_secret_version.assert_called_once_with(\n248:             path=\"khoj/ldap\",\n249:             mount_point=\"secret\"\n250:         )\n251: \n252:     @patch.dict(os.environ, {\n253:         \"KHOJ_VAULT_ADDR\": \"http://vault:8200\",\n254:         \"KHOJ_VAULT_TOKEN\": \"test-token\",\n255:         \"KHOJ_VAULT_PATH\": \"custom/data/app/secrets\"\n256:     }, clear=True)\n257:     @patch('khoj.utils.secrets_vault.hvac.Client')\n258:     def test_uses_custom_vault_path(self, mock_client_class):\n259:         \"\"\"Test that custom Vault path is used when set.\"\"\"\n260:         mock_client_class.return_value = self.mock_client\n261:         \n262:         adapter = VaultAdapter()\n263:         adapter.get_ldap_credentials()\n264:         \n265:         self.mock_client.secrets.kv.v2.read_secret_version.assert_called_once_with(\n266:             path=\"app/secrets\",\n267:             mount_point=\"custom\"\n268:         )\n269: \n270:     @patch.dict(os.environ, {\n271:         \"KHOJ_VAULT_ADDR\": \"http://vault:8200\",\n272:         \"KHOJ_VAULT_TOKEN\": \"test-token\",\n273:         \"KHOJ_VAULT_PATH\": \"secret/data/khoj/ldap\"\n274:     }, clear=True)\n275:     @patch('khoj.utils.secrets_vault.hvac.Client')\n276:     def test_raises_error_when_bind_dn_missing(self, mock_client_class):\n277:         \"\"\"Test that LdapSecretError is raised when bind_dn is missing.\"\"\"\n278:         mock_response = {\n279:             \"data\": {\n280:                 \"data\": {\n281:                     \"bind_password\": \"secret_password_123\"\n282:                 }\n283:             }\n284:         }\n285:         self.mock_client.secrets.kv.v2.read_secret_version.return_value = mock_response\n286:         mock_client_class.return_value = self.mock_client\n287:         \n288:         adapter = VaultAdapter()\n289:         with self.assertRaises(LdapSecretError) as context:\n290:             adapter.get_ldap_credentials()\n291:         self.assertIn(\"missing required fields\", str(context.exception).lower())\n292: \n293:     @patch.dict(os.environ, {\n294:         \"KHOJ_VAULT_ADDR\": \"http://vault:8200\",\n295:         \"KHOJ_VAULT_TOKEN\": \"test-token\",\n296:         \"KHOJ_VAULT_PATH\": \"secret/data/khoj/ldap\"\n297:     }, clear=True)\n298:     @patch('khoj.utils.secrets_vault.hvac.Client')\n299:     def test_raises_error_when_bind_password_missing(self, mock_client_class):\n300:         \"\"\"Test that LdapSecretError is raised when bind_password is missing.\"\"\"\n301:         mock_response = {\n302:             \"data\": {\n303:                 \"data\": {\n304:                     \"bind_dn\": \"CN=service,DC=example,DC=com\"\n305:                 }\n306:             }\n307:         }\n308:         self.mock_client.secrets.kv.v2.read_secret_version.return_value = mock_response\n309:         mock_client_class.return_value = self.mock_client\n310:         \n311:         adapter = VaultAdapter()\n312:         with self.assertRaises(LdapSecretError) as context:\n313:             adapter.get_ldap_credentials()\n314:         self.assertIn(\"missing required fields\", str(context.exception).lower())\n315: \n316:     @patch.dict(os.environ, {\n317:         \"KHOJ_VAULT_ADDR\": \"http://vault:8200\",\n318:         \"KHOJ_VAULT_TOKEN\": \"test-token\",\n319:         \"KHOJ_VAULT_PATH\": \"secret/data/khoj/ldap\"\n320:     }, clear=True)\n321:     @patch('khoj.utils.secrets_vault.hvac.Client')\n322:     def test_raises_error_when_vault_read_fails(self, mock_client_class):\n323:         \"\"\"Test that LdapSecretError is raised when Vault read fails.\"\"\"\n324:         self.mock_client.secrets.kv.v2.read_secret_version.side_effect = Exception(\"Permission denied\")\n325:         mock_client_class.return_value = self.mock_client\n326:         \n327:         adapter = VaultAdapter()\n328:         with self.assertRaises(LdapSecretError) as context:\n329:             adapter.get_ldap_credentials()\n330:         self.assertIn(\"failed to retrieve secrets\", str(context.exception).lower())\n331: \n332: \n333: class TestVaultAdapterCaching(unittest.TestCase):\n334:     \"\"\"Test VaultAdapter caching behavior.\"\"\"\n335: \n336:     def setUp(self):\n337:         \"\"\"Set up test fixtures.\"\"\"\n338:         self.mock_client = MagicMock()\n339:         self.mock_response = {\n340:             \"data\": {\n341:                 \"data\": {\n342:                     \"bind_dn\": \"CN=service,DC=example,DC=com\",\n343:                     \"bind_password\": \"secret_password_123\"\n344:                 }\n345:             }\n346:         }\n347:         self.mock_client.secrets.kv.v2.read_secret_version.return_value = self.mock_response\n348:         self.mock_client.is_authenticated.return_value = True\n349: \n350:     @patch.dict(os.environ, {\n351:         \"KHOJ_VAULT_ADDR\": \"http://vault:8200\",\n352:         \"KHOJ_VAULT_TOKEN\": \"test-token\",\n353:         \"KHOJ_VAULT_PATH\": \"secret/data/khoj/ldap\"\n354:     }, clear=True)\n355:     @patch('khoj.utils.secrets_vault.hvac.Client')\n356:     @patch('khoj.utils.secrets_vault.time.time')\n357:     def test_uses_cache_when_valid(self, mock_time, mock_client_class):\n358:         \"\"\"Test that cached credentials are returned when cache is valid.\"\"\"\n359:         mock_client_class.return_value = self.mock_client\n360:         mock_time.return_value = 1000.0\n361:         \n362:         adapter = VaultAdapter()\n363:         \n364:         # First call - should read from Vault\n365:         adapter.get_ldap_credentials()\n366:         self.assertEqual(self.mock_client.secrets.kv.v2.read_secret_version.call_count, 1)\n367:         \n368:         # Second call - should use cache\n369:         mock_time.return_value = 1100.0  # 100 seconds later (within default 300s TTL)\n370:         adapter.get_ldap_credentials()\n371:         self.assertEqual(self.mock_client.secrets.kv.v2.read_secret_version.call_count, 1)\n372: \n373:     @patch.dict(os.environ, {\n374:         \"KHOJ_VAULT_ADDR\": \"http://vault:8200\",\n375:         \"KHOJ_VAULT_TOKEN\": \"test-token\",\n376:         \"KHOJ_VAULT_PATH\": \"secret/data/khoj/ldap\"\n377:     }, clear=True)\n378:     @patch('khoj.utils.secrets_vault.hvac.Client')\n379:     @patch('khoj.utils.secrets_vault.time.time')\n380:     def test_refreshes_cache_when_expired(self, mock_time, mock_client_class):\n381:         \"\"\"Test that Vault is called again when cache is expired.\"\"\"\n382:         mock_client_class.return_value = self.mock_client\n383:         mock_time.return_value = 1000.0\n384:         \n385:         adapter = VaultAdapter()\n386:         \n387:         # First call - should read from Vault\n388:         adapter.get_ldap_credentials()\n389:         self.assertEqual(self.mock_client.secrets.kv.v2.read_secret_version.call_count, 1)\n390:         \n391:         # Second call after cache expiry - should read from Vault again\n392:         mock_time.return_value = 1500.0  # 500 seconds later (beyond default 300s TTL)\n393:         adapter.get_ldap_credentials()\n394:         self.assertEqual(self.mock_client.secrets.kv.v2.read_secret_version.call_count, 2)\n395: \n396:     @patch.dict(os.environ, {\n397:         \"KHOJ_VAULT_ADDR\": \"http://vault:8200\",\n398:         \"KHOJ_VAULT_TOKEN\": \"test-token\",\n399:         \"KHOJ_VAULT_PATH\": \"secret/data/khoj/ldap\"\n400:     }, clear=True)\n401:     @patch('khoj.utils.secrets_vault.hvac.Client')\n402:     def test_clear_cache_empties_cache(self, mock_client_class):\n403:         \"\"\"Test that clear_cache empties the cache.\"\"\"\n404:         mock_client_class.return_value = self.mock_client\n405:         \n406:         adapter = VaultAdapter()\n407:         \n408:         # First call to populate cache\n409:         adapter.get_ldap_credentials()\n410:         self.assertTrue(adapter._cache)\n411:         \n412:         # Clear cache\n413:         adapter.clear_cache()\n414:         self.assertFalse(adapter._cache)\n415:         self.assertEqual(adapter._cache_timestamp, 0)\n416: \n417: \n418: class TestVaultAdapterLogging(unittest.TestCase):\n419:     \"\"\"Test that no secrets are logged by VaultAdapter.\"\"\"\n420: \n421:     def setUp(self):\n422:         \"\"\"Set up test fixtures.\"\"\"\n423:         self.mock_client = MagicMock()\n424:         self.mock_response = {\n425:             \"data\": {\n426:                 \"data\": {\n427:                     \"bind_dn\": \"CN=service,DC=example,DC=com\",\n428:                     \"bind_password\": \"secret_password_123\"\n429:                 }\n430:             }\n431:         }\n432:         self.mock_client.secrets.kv.v2.read_secret_version.return_value = self.mock_response\n433:         self.mock_client.is_authenticated.return_value = True\n434: \n435:     @patch.dict(os.environ, {\n436:         \"KHOJ_VAULT_ADDR\": \"http://vault:8200\",\n437:         \"KHOJ_VAULT_TOKEN\": \"test-token\",\n438:         \"KHOJ_VAULT_PATH\": \"secret/data/khoj/ldap\"\n439:     }, clear=True)\n440:     @patch('khoj.utils.secrets_vault.hvac.Client')\n441:     @patch('khoj.utils.secrets_vault.logger')\n442:     def test_debug_logs_do_not_contain_password(self, mock_logger, mock_client_class):\n443:         \"\"\"Test that debug log messages don't contain the password.\"\"\"\n444:         mock_client_class.return_value = self.mock_client\n445:         \n446:         adapter = VaultAdapter()\n447:         adapter.get_ldap_credentials()\n448:         \n449:         # Check that debug logs were called\n450:         debug_calls = [call for call in mock_logger.debug.call_args_list]\n451:         self.assertTrue(len(debug_calls) > 0)\n452:         \n453:         # Verify no log message contains the actual password\n454:         for call in mock_logger.debug.call_args_list:\n455:             log_message = str(call)\n456:             self.assertNotIn(\"secret_password_123\", log_message)\n457: \n458:     @patch.dict(os.environ, {\n459:         \"KHOJ_VAULT_ADDR\": \"http://vault:8200\",\n460:         \"KHOJ_VAULT_TOKEN\": \"test-token\",\n461:         \"KHOJ_VAULT_PATH\": \"secret/data/khoj/ldap\"\n462:     }, clear=True)\n463:     @patch('khoj.utils.secrets_vault.hvac.Client')\n464:     @patch('khoj.utils.secrets_vault.logger')\n465:     def test_error_logs_do_not_contain_password(self, mock_logger, mock_client_class):\n466:         \"\"\"Test that error log messages don't contain the password.\"\"\"\n467:         self.mock_client.secrets.kv.v2.read_secret_version.side_effect = Exception(\"Permission denied\")\n468:         mock_client_class.return_value = self.mock_client\n469:         \n470:         adapter = VaultAdapter()\n471:         with self.assertRaises(LdapSecretError):\n472:             adapter.get_ldap_credentials()\n473:         \n474:         # Check that error was logged\n475:         mock_logger.error.assert_called()\n476:         \n477:         # Verify no log message contains the password\n478:         for call in mock_logger.error.call_args_list:\n479:             log_message = str(call)\n480:             self.assertNotIn(\"secret_password_123\", log_message)\n481: \n482: \n483: class TestGetLdapCredentialsFromVault(unittest.TestCase):\n484:     \"\"\"Test get_ldap_credentials_from_vault convenience function.\"\"\"\n485: \n486:     def setUp(self):\n487:         \"\"\"Set up test fixtures.\"\"\"\n488:         self.mock_client = MagicMock()\n489:         self.mock_response = {\n490:             \"data\": {\n491:                 \"data\": {\n492:                     \"bind_dn\": \"CN=service,DC=example,DC=com\",\n493:                     \"bind_password\": \"secret_password_123\"\n494:                 }\n495:             }\n496:         }\n497:         self.mock_client.secrets.kv.v2.read_secret_version.return_value = self.mock_response\n498:         self.mock_client.is_authenticated.return_value = True\n499: \n500:     @patch.dict(os.environ, {\n501:         \"KHOJ_VAULT_ADDR\": \"http://vault:8200\",\n502:         \"KHOJ_VAULT_TOKEN\": \"test-token\",\n503:         \"KHOJ_VAULT_PATH\": \"secret/data/khoj/ldap\"\n504:     }, clear=True)\n505:     @patch('khoj.utils.secrets_vault.hvac.Client')\n506:     def test_returns_credentials(self, mock_client_class):\n507:         \"\"\"Test that the convenience function returns credentials.\"\"\"\n508:         mock_client_class.return_value = self.mock_client\n509:         \n510:         bind_dn, bind_password = get_ldap_credentials_from_vault()\n511:         \n512:         self.assertEqual(bind_dn, \"CN=service,DC=example,DC=com\")\n513:         self.assertEqual(bind_password, \"secret_password_123\")\n514: \n515:     @patch.dict(os.environ, {}, clear=True)\n516:     def test_raises_error_when_not_configured(self):\n517:         \"\"\"Test that LdapSecretError is raised when Vault is not configured.\"\"\"\n518:         with self.assertRaises(LdapSecretError):\n519:             get_ldap_credentials_from_vault()\n520: \n521: \n522: class TestVaultPathParsing(unittest.TestCase):\n523:     \"\"\"Test Vault path parsing for different formats.\"\"\"\n524: \n525:     def setUp(self):\n526:         \"\"\"Set up test fixtures.\"\"\"\n527:         self.mock_client = MagicMock()\n528:         self.mock_response = {\n529:             \"data\": {\n530:                 \"data\": {\n531:                     \"bind_dn\": \"CN=service,DC=example,DC=com\",\n532:                     \"bind_password\": \"secret_password_123\"\n533:                 }\n534:             }\n535:         }\n536:         self.mock_client.secrets.kv.v2.read_secret_version.return_value = self.mock_response\n537:         self.mock_client.is_authenticated.return_value = True\n538: \n539:     @patch.dict(os.environ, {\n540:         \"KHOJ_VAULT_ADDR\": \"http://vault:8200\",\n541:         \"KHOJ_VAULT_TOKEN\": \"test-token\",\n542:         \"KHOJ_VAULT_PATH\": \"secret/data/khoj/ldap\"\n543:     }, clear=True)\n544:     @patch('khoj.utils.secrets_vault.hvac.Client')\n545:     def test_parses_standard_kv_v2_path(self, mock_client_class):\n546:         \"\"\"Test parsing of standard KV v2 path format.\"\"\"\n547:         mock_client_class.return_value = self.mock_client\n548:         \n549:         adapter = VaultAdapter()\n550:         adapter.get_ldap_credentials()\n551:         \n552:         self.mock_client.secrets.kv.v2.read_secret_version.assert_called_once_with(\n553:             path=\"khoj/ldap\",\n554:             mount_point=\"secret\"\n555:         )\n556: \n557:     @patch.dict(os.environ, {\n558:         \"KHOJ_VAULT_ADDR\": \"http://vault:8200\",\n559:         \"KHOJ_VAULT_TOKEN\": \"test-token\",\n560:         \"KHOJ_VAULT_PATH\": \"secret/data/deep/nested/path\"\n561:     }, clear=True)\n562:     @patch('khoj.utils.secrets_vault.hvac.Client')\n563:     def test_parses_deeply_nested_path(self, mock_client_class):\n564:         \"\"\"Test parsing of deeply nested path.\"\"\"\n565:         mock_client_class.return_value = self.mock_client\n566:         \n567:         adapter = VaultAdapter()\n568:         adapter.get_ldap_credentials()\n569:         \n570:         self.mock_client.secrets.kv.v2.read_secret_version.assert_called_once_with(\n571:             path=\"deep/nested/path\",\n572:             mount_point=\"secret\"\n573:         )\n574: \n575:     @patch.dict(os.environ, {\n576:         \"KHOJ_VAULT_ADDR\": \"http://vault:8200\",\n577:         \"KHOJ_VAULT_TOKEN\": \"test-token\",\n578:         \"KHOJ_VAULT_PATH\": \"kv/secret/path\"\n579:     }, clear=True)\n580:     @patch('khoj.utils.secrets_vault.hvac.Client')\n581:     def test_handles_path_without_data_prefix(self, mock_client_class):\n582:         \"\"\"Test handling of path without /data/ prefix.\"\"\"\n583:         mock_client_class.return_value = self.mock_client\n584:         \n585:         adapter = VaultAdapter()\n586:         adapter.get_ldap_credentials()\n587:         \n588:         self.mock_client.secrets.kv.v2.read_secret_version.assert_called_once_with(\n589:             path=\"secret/path\",\n590:             mount_point=\"kv\"\n591:         )\n592: \n593: \n594: if __name__ == '__main__':\n595:     unittest.main(verbosity=2)\n\n(End of file - total 595 lines)\n</content>","timestamp":1772936036748,"originalBytes":26528}